xmle/__init__.py
xmle/_version.py
xmle/colors.py
xmle/elem.py
xmle/file_util.py
xmle/html_table_to_txt.py
xmle/numbered.py
xmle/reporter.py
xmle/restructuredtext.py
xmle/styles.py
xmle/uid.py
xmle/xhtml.py
xmle-0.1.27.dist-info/licenses/LICENSE
xmle-0.1.27.dist-info/METADATA
xmle-0.1.27.dist-info/WHEEL
xmle-0.1.27.dist-info/top_level.txt
xmle-0.1.27.dist-info/RECORD
