Metadata-Version: 2.4
Name: xmle
Version: 0.1.27
Summary: An extension to xml.etree.ElementTree.Element to handle xml snippets
Author-email: Jeffrey Newman <jeff@driftless.xyz>
License: MIT
Requires-Python: >=3.8
License-File: LICENSE
Provides-Extra: dev
Requires-Dist: pytest; extra == "dev"
Requires-Dist: jupyter; extra == "dev"
Requires-Dist: pandas; extra == "dev"
Requires-Dist: altair; extra == "dev"
Requires-Dist: docutils; extra == "dev"
Requires-Dist: networkx; extra == "dev"
Requires-Dist: pydot; extra == "dev"
Requires-Dist: vl-convert-python; extra == "dev"
Dynamic: license-file
